{"Script":{"line":"더 많은 서비스를 경험하시길 바랍니다","line_timestamp":"더 많은 서비스를 경험하시길 바랍니다*800","gesture":[{"controller":"Base","type":"Base_Basepose_1_1","pre":[["t0","t2"]],"stroke":[],"relax":[],"pose":1,"relative":0,"periodic":0},{"controller":"BothArm1","type":"Point_Plural_BothArm_All","pre":[["t0","t4"]],"stroke":[["t4","t11"]],"relax":[["t11","t15"]],"pose":0,"relative":0,"periodic":0},{"controller":"Head1","type":"Head_NodDown_5","pre":[],"stroke":[["t13","t17"],["t17","t20"]],"relax":[],"pose":0,"relative":1,"periodic":1},{"controller":"Head1","type":"Head_NodDown_2","pre":[],"stroke":[["t0","t5"],["t5","t9"]],"relax":[],"pose":0,"relative":1,"periodic":1}],"gesture_schedule":[{"controller":"Base","type":"Base_Basepose_1_1","pose":1,"relative":0,"periodic":0,"phase":"pre","start":6,"duration":207},{"controller":"BothArm1","type":"Point_Plural_BothArm_All","pose":0,"relative":0,"periodic":0,"phase":"pre","start":6,"duration":433},{"controller":"BothArm1","type":"Point_Plural_BothArm_All","pose":0,"relative":0,"periodic":0,"phase":"stroke","start":439,"duration":834},{"controller":"BothArm1","type":"Point_Plural_BothArm_All","pose":0,"relative":0,"periodic":0,"phase":"relax","start":1273,"duration":496},{"controller":"Head1","type":"Head_NodDown_5","pose":0,"relative":1,"periodic":1,"phase":"stroke","start":1521,"duration":562},{"controller":"Head1","type":"Head_NodDown_5","pose":0,"relative":1,"periodic":1,"phase":"stroke","start":2083,"duration":570},{"controller":"Head1","type":"Head_NodDown_2","pose":0,"relative":1,"periodic":1,"phase":"stroke","start":6,"duration":548},{"controller":"Head1","type":"Head_NodDown_2","pose":0,"relative":1,"periodic":1,"phase":"stroke","start":554,"duration":476}],"face":[{"controller":"Face","type":"Hopeful","relax":[],"stroke":[["t0","t2"]]},{"controller":"Face","type":"Hopeful","relax":[["t13","t15"]],"stroke":[]}],"face_schedule":[{"controller":"Face","type":"Hopeful","duration":207,"phase":"stroke","start":6},{"controller":"Face","type":"Hopeful","duration":248,"phase":"relax","start":1521}],"command":[{"controller":"Turn","command":"ROTATE_TO_MAINTARGET","stroke":[["t20","t21"]],"relax":[],"id":0}],"command_schedule":[{"controller":"Turn","command":"ROTATE_TO_MAINTARGET","phase":"stroke","relax":[],"id":0,"start":2653,"duration":800}],"ui":[{"controller":"UI","type":"image_panel","name":"ContentsInfo","function":"Close","param1":"","param2":"","stroke":[["t19","t20"]]}],"SpecialCommands":null,"audio_id":"smart-guro-1-16","audio_schedule":[{"type":"start","time":0},{"type":"stop","time":2716}],"ui_schedule":[{"controller":"UI","type":"image_panel","name":"ContentsInfo","start":2461,"function":"Close","param1":"","param2":""}],"duration":3516,"name":"action","sound_schedule":[],"Description":"","Date":"2019.08.26-18.06.53","sound":[]}}