{"Id": "0", "Script": {"word_time": [{"word": "\uc624\ub298", "timeTag": ["t0", "t2"]}, {"word": "\uc6b0\ub9ac", "timeTag": ["t3", "t5"]}, {"word": "\ubd80\uc2a4", "timeTag": ["t6", "t8"]}, {"word": "\uc911\uc5d0", "timeTag": ["t9", "t11"]}, {"word": "\uc9c0\uae08", "timeTag": ["t12", "t14"]}, {"word": "\ub9d0\uc500\ub4dc\ub9b0", "timeTag": ["t15", "t19"]}, {"word": "\uac83\uacfc", "timeTag": ["t20", "t22"]}, {"word": "\uad00\ub828\ub41c", "timeTag": ["t23", "t26"]}, {"word": "\ub0b4\uc6a9\uc774", "timeTag": ["t27", "t30"]}, {"word": "\uc788\ub2e4\ub294", "timeTag": ["t31", "t34"]}, {"word": "\uac83", "timeTag": ["t35", "t36"]}, {"word": "\uc544\uc138\uc694?", "timeTag": ["t37", "t41"]}], "Flag": {"Upper": 2, "Rotate": 2, "Head": 2}, "char_time": [{"character": "\uc624", "timeTag": "t0"}, {"character": "\ub298", "timeTag": "t1"}, {"character": " ", "timeTag": "t2"}, {"character": "\uc6b0", "timeTag": "t3"}, {"character": "\ub9ac", "timeTag": "t4"}, {"character": " ", "timeTag": "t5"}, {"character": "\ubd80", "timeTag": "t6"}, {"character": "\uc2a4", "timeTag": "t7"}, {"character": " ", "timeTag": "t8"}, {"character": "\uc911", "timeTag": "t9"}, {"character": "\uc5d0", "timeTag": "t10"}, {"character": " ", "timeTag": "t11"}, {"character": "\uc9c0", "timeTag": "t12"}, {"character": "\uae08", "timeTag": "t13"}, {"character": " ", "timeTag": "t14"}, {"character": "\ub9d0", "timeTag": "t15"}, {"character": "\uc500", "timeTag": "t16"}, {"character": "\ub4dc", "timeTag": "t17"}, {"character": "\ub9b0", "timeTag": "t18"}, {"character": " ", "timeTag": "t19"}, {"character": "\uac83", "timeTag": "t20"}, {"character": "\uacfc", "timeTag": "t21"}, {"character": " ", "timeTag": "t22"}, {"character": "\uad00", "timeTag": "t23"}, {"character": "\ub828", "timeTag": "t24"}, {"character": "\ub41c", "timeTag": "t25"}, {"character": " ", "timeTag": "t26"}, {"character": "\ub0b4", "timeTag": "t27"}, {"character": "\uc6a9", "timeTag": "t28"}, {"character": "\uc774", "timeTag": "t29"}, {"character": " ", "timeTag": "t30"}, {"character": "\uc788", "timeTag": "t31"}, {"character": "\ub2e4", "timeTag": "t32"}, {"character": "\ub294", "timeTag": "t33"}, {"character": " ", "timeTag": "t34"}, {"character": "\uac83", "timeTag": "t35"}, {"character": " ", "timeTag": "t36"}, {"character": "\uc544", "timeTag": "t37"}, {"character": "\uc138", "timeTag": "t38"}, {"character": "\uc694", "timeTag": "t39"}, {"character": "?", "timeTag": "t40"}], "gesture": [{"pre": [["t0", "t3"]], "relax": [], "periodic": 0, "pose": 0, "stroke_hold": [], "relative": 0, "type": "Point_Who_RArm_Me_1", "stroke": [["t3", "t6"]], "pre_hold": [], "controller": "RArm1"}, {"pre": [["t6", "t10"]], "relax": [["t31", "t34"]], "periodic": 0, "pose": 0, "stroke_hold": [], "relative": 0, "type": "Hand_Side_Make_3_3_1", "stroke": [["t10", "t16"]], "pre_hold": [], "controller": "RArm1"}, {"pre": [], "relax": [["t27", "t32"]], "periodic": 0, "pose": 0, "stroke_hold": [], "relative": 1, "type": "HandRel_ToR_2", "stroke": [["t19", "t27"]], "pre_hold": [], "controller": "RArm2"}, {"pre": [["t30", "t35"]], "relax": [], "periodic": 0, "pose": 1, "stroke_hold": [], "relative": 0, "type": "Base_Basepose_3_2", "stroke": [], "pre_hold": [], "controller": "Base"}, {"pre": [], "relax": [], "periodic": 1, "pose": 0, "stroke_hold": [], "relative": 1, "type": "Head_TiltR_3", "stroke": [["t34", "t38"], ["t38", "t41"]], "pre_hold": [], "controller": "Head1"}], "panel_schedule": [], "ui": [], "duration": 4414, "command": [], "gesture_schedule": [{"phase": "pre", "periodic": 0, "pose": 0, "relative": 0, "start": 6, "type": "Point_Who_RArm_Me_1", "duration": 302, "controller": "RArm1"}, {"phase": "stroke", "periodic": 0, "pose": 0, "relative": 0, "start": 308, "type": "Point_Who_RArm_Me_1", "duration": 242, "controller": "RArm1"}, {"phase": "pre", "periodic": 0, "pose": 0, "relative": 0, "start": 550, "type": "Hand_Side_Make_3_3_1", "duration": 390, "controller": "RArm1"}, {"phase": "stroke", "periodic": 0, "pose": 0, "relative": 0, "start": 940, "type": "Hand_Side_Make_3_3_1", "duration": 601, "controller": "RArm1"}, {"phase": "relax", "periodic": 0, "pose": 0, "relative": 0, "start": 3246, "type": "Hand_Side_Make_3_3_1", "duration": 297, "controller": "RArm1"}, {"phase": "stroke", "periodic": 0, "pose": 0, "relative": 1, "start": 1916, "type": "HandRel_ToR_2", "duration": 982, "controller": "RArm2"}, {"phase": "relax", "periodic": 0, "pose": 0, "relative": 1, "start": 2898, "type": "HandRel_ToR_2", "duration": 447, "controller": "RArm2"}, {"phase": "pre", "periodic": 0, "pose": 1, "relative": 0, "start": 3159, "type": "Base_Basepose_3_2", "duration": 484, "controller": "Base"}, {"phase": "stroke", "periodic": 1, "pose": 0, "relative": 1, "start": 3543, "type": "Head_TiltR_3", "duration": 395, "controller": "Head1"}, {"phase": "stroke", "periodic": 1, "pose": 0, "relative": 1, "start": 3938, "type": "Head_TiltR_3", "duration": 417, "controller": "Head1"}], "line": "\uc624\ub298 \uc6b0\ub9ac \ubd80\uc2a4 \uc911\uc5d0 \uc9c0\uae08 \ub9d0\uc500\ub4dc\ub9b0 \uac83\uacfc \uad00\ub828\ub41c \ub0b4\uc6a9\uc774 \uc788\ub2e4\ub294 \uac83 \uc544\uc138\uc694?", "line_timestamp": "\uc624\ub298 \uc6b0\ub9ac \ubd80\uc2a4 \uc911\uc5d0 \uc9c0\uae08 \ub9d0\uc500\ub4dc\ub9b0 \uac83\uacfc \uad00\ub828\ub41c \ub0b4\uc6a9\uc774 \uc788\ub2e4\ub294 \uac83 \uc544\uc138\uc694?", "NonTextTimestamp": [], "blink_schedule": [], "command_schedule": [], "blink": [], "name": "action", "face": [{"type": "Smile", "stroke": [["t3", "t4"], ["t14", "t15"], ["t35", "t36"]], "relax": [["t11", "t12"], ["t22", "t23"], ["t40", "t41"]], "stroke_hold": [], "controller": "Face"}], "audio_schedule": [{"type": "start", "time": 0}, {"type": "stop", "time": 4414}], "audio_id": "booth_5_01_003", "SpecialCommands": [], "face_schedule": [{"start": 308, "type": "Smile", "duration": 80, "phase": "stroke", "controller": "Face"}, {"start": 1318, "type": "Smile", "duration": 98, "phase": "stroke", "controller": "Face"}, {"start": 3643, "type": "Smile", "duration": 78, "phase": "stroke", "controller": "Face"}, {"start": 1031, "type": "Smile", "duration": 93, "phase": "relax", "controller": "Face"}, {"start": 2264, "type": "Smile", "duration": 110, "phase": "relax", "controller": "Face"}, {"start": 4214, "type": "Smile", "duration": 141, "phase": "relax", "controller": "Face"}]}}