{"Script":{"line":"감사합니다","line_timestamp":"*300*500감사합니다","gesture":[{"controller":"FullBody1","type":"UpperBody_BowPush_2","pre":[["t0","t1"]],"stroke":[["t1","t2"]],"relax":[["t2","t7"]],"pose":0,"relative":1,"periodic":0},{"controller":"Head3","type":"Evaluation_Negative_Head_4","pre":[],"stroke":[["t2","t5"]],"relax":[["t5","t7"]],"pose":0,"relative":0,"periodic":0}],"gesture_schedule":[{"controller":"FullBody1","type":"UpperBody_BowPush_2","pose":0,"relative":1,"periodic":0,"phase":"pre","start":0,"duration":306},{"controller":"FullBody1","type":"UpperBody_BowPush_2","pose":0,"relative":1,"periodic":0,"phase":"stroke","start":306,"duration":500},{"controller":"FullBody1","type":"UpperBody_BowPush_2","pose":0,"relative":1,"periodic":0,"phase":"relax","start":806,"duration":987},{"controller":"Head3","type":"Evaluation_Negative_Head_4","pose":0,"relative":0,"periodic":0,"phase":"stroke","start":806,"duration":591},{"controller":"Head3","type":"Evaluation_Negative_Head_4","pose":0,"relative":0,"periodic":0,"phase":"relax","start":1397,"duration":396}],"face":[{"controller":"Face","type":"Amused","relax":[["t5","t7"]],"stroke":[["t2","t5"]]}],"face_schedule":[{"controller":"Face","type":"Amused","duration":591,"phase":"stroke","start":806},{"controller":"Face","type":"Amused","duration":396,"phase":"relax","start":1397}],"command":[],"command_schedule":[],"ui":[{"controller":"UI","type":"image_panel","name":"","function":"Close","param1":"FadeOut","param2":"","stroke":[["t0","t1"]]}],"SpecialCommands":null,"audio_id":"airi_12","audio_schedule":[{"type":"start","time":300},{"type":"pause","time":306},{"type":"resume","time":806},{"type":"stop","time":1871}],"ui_schedule":[{"controller":"UI","type":"image_panel","name":"","start":0,"function":"Close","param1":"FadeOut","param2":""}],"duration":1871,"name":"action","sound_schedule":[],"NonTextTimestamp":null,"Description":"","Date":"2019.06.23-17.40.11","sound":[]}}