{"Script":{"line":"김동엽님은","line_timestamp":"김동엽님은","gesture_schedule":[{"controller":"FullBody1","type":"UpperBody_TiltR_1","pose":0,"relative":1,"periodic":1,"phase":"stroke","start":6,"duration":597},{"controller":"FullBody1","type":"UpperBody_TiltR_1","pose":0,"relative":1,"periodic":1,"phase":"relax","start":603,"duration":398},{"controller":"Head1","type":"Head_Nod_2","pose":0,"relative":1,"periodic":1,"phase":"stroke","start":6,"duration":398},{"controller":"Head1","type":"Head_Nod_2","pose":0,"relative":1,"periodic":1,"phase":"relax","start":404,"duration":597}],"face_schedule":[{"controller":"Face","type":"Amused","duration":398,"phase":"stroke","start":6},{"controller":"Face","type":"Amused","duration":597,"phase":"relax","start":404}],"command_schedule":[],"SpecialCommands":null,"audio_id":"calling_2_6","audio_schedule":[{"type":"start","time":0},{"type":"stop","time":1071}],"ui_schedule":[],"duration":1071,"name":"action","sound_schedule":[],"NonTextTimestamp":null,"Description":"","Date":"2019.06.13-19.59.29"}}