{"Script":{"line":"어느 분을 만나러 오셨는지 말씀해 주십시오","line_timestamp":"어느 분을 만나러 오셨는지 말씀해 주십시오","gesture_schedule":[{"controller":"BothArm1","type":"Point_Who_BothArm_Yous_1","pose":0,"relative":0,"periodic":0,"phase":"pre","start":6,"duration":460},{"controller":"BothArm1","type":"Point_Who_BothArm_Yous_1","pose":0,"relative":0,"periodic":0,"phase":"stroke","start":466,"duration":774},{"controller":"BothArm1","type":"Point_Who_BothArm_Yous_1","pose":0,"relative":0,"periodic":0,"phase":"relax","start":2220,"duration":649},{"controller":"Head1","type":"Head_NodDown_3","pose":0,"relative":1,"periodic":1,"phase":"stroke","start":1464,"duration":595},{"controller":"Head1","type":"Head_NodDown_3","pose":0,"relative":1,"periodic":1,"phase":"stroke","start":2059,"duration":810}],"face_schedule":[{"controller":"Face","type":"Amused","duration":172,"phase":"stroke","start":6},{"controller":"Face","type":"Amused","duration":327,"phase":"relax","start":2542}],"command_schedule":[],"SpecialCommands":null,"audio_id":"who_2","audio_schedule":[{"type":"start","time":0},{"type":"stop","time":2951}],"ui_schedule":[],"duration":2951,"name":"action","sound_schedule":[],"NonTextTimestamp":null,"Description":"WhoWindow를 보여주면서","Date":"2019.06.13-20.45.00"}}